<?xml version="1.0" encoding="UTF-8"?>
  <?xml-stylesheet type="text/xsl" href="rfc2629.xslt" ?>
  <!-- generated by https://github.com/cabo/kramdown-rfc version 1.6.37 (Ruby 3.0.2) -->


<!DOCTYPE rfc  [
  <!ENTITY nbsp    "&#160;">
  <!ENTITY zwsp   "&#8203;">
  <!ENTITY nbhy   "&#8209;">
  <!ENTITY wj     "&#8288;">

]>


<rfc ipr="full3978trust200902" docName="draft-ietf-acme-dns-account-challenge-02" category="std" consensus="true" tocInclude="true" sortRefs="true" symRefs="true">
  <front>
    <title abbrev="ACME-DNS-CHALLENGE">Automated Certificate Management Environment (ACME) DNS Labeled With ACME Account ID Challenge</title>

    <author fullname="Antonios A. Chariton">
      <organization>Independent Contributor</organization>
      <address>
        <email>daknob@daknob.net</email>
      </address>
    </author>
    <author fullname="Amir A. Omidi">
      <organization>Google</organization>
      <address>
        <email>aaomidi@google.com</email>
      </address>
    </author>
    <author fullname="James Kasten">
      <organization>Google</organization>
      <address>
        <email>jdkasten@google.com</email>
      </address>
    </author>
    <author fullname="Fotis Loukos">
      <organization>Google</organization>
      <address>
        <email>fotisl@google.com</email>
      </address>
    </author>
    <author fullname="Stanislaw A. Janikowski">
      <organization>Google</organization>
      <address>
        <email>stanwise@google.com</email>
      </address>
    </author>

    <date year="2023" month="July" day="09"/>

    <area>Security</area>
    <workgroup>Automated Certificate Management Environment</workgroup>
    <keyword>acme</keyword>

    <abstract>


<?line 52?>

<t>This document outlines a new challenge for the ACME protocol, enabling an ACME
client to answer a domain control validation challenge from an ACME server
using a DNS resource linked to the ACME Account ID. This allows multiple
systems or environments to handle challenge-solving for a single domain.</t>



    </abstract>

    <note title="About This Document" removeInRFC="true">
      <t>
        The latest revision of this draft can be found at <eref target="https://aaomidi.github.io/draft-ietf-acme-dns-account-challenge"/>.
        Status information for this document may be found at <eref target="https://datatracker.ietf.org/doc/draft-ietf-acme-dns-account-challenge/"/>.
      </t>
      <t>
        Discussion of this document takes place on the
        WG Working Group mailing list (<eref target="mailto:acme@ietf.org"/>),
        which is archived at <eref target="https://datatracker.ietf.org/wg/acme/about/"/>.
        Subscribe at <eref target="https://www.ietf.org/mailman/listinfo/acme/"/>.
      </t>
      <t>Source for this draft and an issue tracker can be found at
        <eref target="https://github.com/aaomidi/draft-ietf-acme-dns-account-challenge"/>.</t>
    </note>


  </front>

  <middle>


<?line 59?>

<section anchor="introduction"><name>Introduction</name>

<t>The <spanx style="verb">dns-01</spanx> challenge specified in section 8.4 of <xref target="RFC8555"/> requires that
ACME clients validate the domain under the <spanx style="verb">_acme-challenge</spanx> label for the
<spanx style="verb">TXT</spanx> record. This unique label creates an impediment limiting the number of
other entities domain validation can be delegated to.</t>

<t>In multi-region deployments, where separate availability zones serve the same
content, and dependencies across them are avoided, operators need a way to
obtain a separate certificate per zone, for the same domain name. Similarly, in
cases of zero-downtime migration, two different setups of the infrastructure
may coexist for a long period of time, and both need access to valid
certificates.</t>

<t>Due to the uniqueness of the <spanx style="verb">_acme-challenge</spanx> label, operators today have to
pick a single ACME challenge solver for their domain name, and then add a
<spanx style="verb">CNAME</spanx> record to this infrastructure. A domain name can only have one <spanx style="verb">CNAME</spanx>
in DNS.</t>

<t>This document specifies a new challenge type, <spanx style="verb">dns-account-01</spanx>. This challenge
leverages the ACME Account Resource URL to present an account-unique stable
challenge to an ACME server. This challenge allows any domain name to delegate
its domain validation to more than one service through ACME account-unique DNS
records.</t>

<t>As now multiple labels can be used to prove domain control, and they depend on
the ACME account, any number of them can be generated in advance, and then all
required <spanx style="verb">CNAME</spanx> records can be created statically. The dynamic part of the
label depends on the ACME account and not the account key, to allow for
seamless account key rollover without the label changing. This ensures very
long-lived labels, without any security considerations.</t>

<t>This RFC does not intend to deprecate the <spanx style="verb">dns-01</spanx> challenge specified in
<xref target="RFC8555"/>. Since this new challenge does not modify or build on any
pre-existing challenges, the ability to complete the <spanx style="verb">dns-account-01</spanx> challenge
requires ACME server operators to deploy new changes to their codebase. This
makes adopting and using this challenge an opt-in process.</t>

</section>
<section anchor="conventions-and-definitions"><name>Conventions and Definitions</name>

<t>The key words "<bcp14>MUST</bcp14>", "<bcp14>MUST NOT</bcp14>", "<bcp14>REQUIRED</bcp14>", "<bcp14>SHALL</bcp14>", "<bcp14>SHALL
NOT</bcp14>", "<bcp14>SHOULD</bcp14>", "<bcp14>SHOULD NOT</bcp14>", "<bcp14>RECOMMENDED</bcp14>", "<bcp14>NOT RECOMMENDED</bcp14>",
"<bcp14>MAY</bcp14>", and "<bcp14>OPTIONAL</bcp14>" in this document are to be interpreted as
described in BCP 14 <xref target="RFC2119"/> <xref target="RFC8174"/> when, and only when, they
appear in all capitals, as shown here.</t>

<?line -18?>

</section>
<section anchor="dns-account-01-challenge"><name>DNS-ACCOUNT-01 Challenge</name>

<t>When the identifier being validated is a domain name, the client can prove control of that domain by provisioning a <spanx style="verb">TXT</spanx> resource record containing a designated value for a specific validation domain name.</t>

<t><list style="symbols">
  <t>type (required, string): The string "dns-account-01".</t>
  <t>token (required, string): A random value that uniquely identifies the challenge. This value <bcp14>MUST</bcp14> have at least 128 bits of entropy. It <bcp14>MUST NOT</bcp14> contain any characters outside the base64url alphabet, including padding characters ("="). See <xref target="RFC4086"/> for additional information on additional requirements for secure randomness.</t>
</list></t>

<figure><artwork><![CDATA[
{
    "type": "dns-account-01",
    "url": "https://example.com/acme/chall/i00MGYwLWIx",
    "status": "pending",
    "token": "ODE4OWY4NTktYjhmYS00YmY1LTk5MDgtZTFjYTZmNjZlYTUx"
}
]]></artwork></figure>

<t>A client can fulfill this challenge by performing the following steps:</t>

<t><list style="symbols">
  <t>Construct a key authorization <xref section="8.1" sectionFormat="comma" target="RFC8555"/> from the <spanx style="verb">token</spanx> value provided in the challenge and the client's account key</t>
  <t>Compute the SHA-256 digest <xref target="FIPS180-4"/> of the key authorization</t>
  <t>Construct the validation domain name by prepending the following label to the domain name being validated:  <vspace blankLines='1'/>
    <figure><artwork><![CDATA[
"_acme-challenge_" || base32(SHA-256(Account Resource URL)[0:9])
]]></artwork></figure>
  <list style="symbols">
      <t>SHA-256 is the SHA hashing operation defined in <xref target="RFC6234"/></t>
      <t><spanx style="verb">[0:9]</spanx> is the operation that selects the first ten bytes (bytes 0 through 9 inclusive) from the previous SHA256 operation</t>
      <t>base32 is the operation defined in <xref target="RFC4648"/></t>
      <t>Account Resource URL is defined in <xref section="7.3" sectionFormat="comma" target="RFC8555"/> as the value in the Location header field</t>
      <t>The <spanx style="verb">"||"</spanx> operator indicates concatenation of strings</t>
    </list></t>
  <t>Provision a DNS <spanx style="verb">TXT</spanx> record with the base64url digest value under the constructed domain validation name</t>
</list></t>

<t>For example, if the domain name being validated is "www.example.org", and the account URL of "https://example.com/acme/acct/ExampleAccount" then the client would provision the following DNS record:</t>

<figure><artwork><![CDATA[
_acme-challenge_ujmmovf2vn55tgye.www.example.org 300 IN TXT "LoqXcYV8...jxAjEuX0.9jg46WB3...fm21mqTI"
]]></artwork></figure>

<t>(In the above, "..." indicates that the token and the JWK thumbprint in the key authorization have been truncated to fit on the page.)</t>

<t>Respond to the ACME server with an empty object ({}) to acknowledge that the challenge can be validated by the server</t>

<figure><artwork><![CDATA[
POST /acme/chall/Rg5dV14Gh1Q
Host: example.com
Content-Type: application/jose+json

{
  "protected": base64url({
    "alg": "ES256",
    "kid": "https://example.com/acme/acct/evOfKhNU60wg",
    "nonce": "SS2sSl1PtspvFZ08kNtzKd",
    "url": "https://example.com/acme/chall/Rg5dV14Gh1Q"
  }),
  "payload": base64url({}),
  "signature": "Q1bURgJoEslbD1c5...3pYdSMLio57mQNN4"
}
]]></artwork></figure>

<t>On receiving a response, the server constructs and stores the key authorization from the challenge <spanx style="verb">token</spanx> value and the current client account key.</t>

<t>To validate the <spanx style="verb">dns-account-01</spanx> challenge, the server performs the following steps:</t>

<t><list style="symbols">
  <t>Compute the SHA-256 digest <xref target="FIPS180-4"/> of the stored key authorization</t>
  <t>Compute the validation domain name with the account URL of the ACME account requesting validation</t>
  <t>Query for <spanx style="verb">TXT</spanx> records for the validation domain name</t>
  <t>Verify that the contents of one of the TXT records match the digest value</t>
</list></t>

<t>If all the above verifications succeed, then the validation is successful. If no DNS record is found, or DNS record and response payload do not pass these checks, then the server <bcp14>MUST</bcp14> fail the validation and mark the challenge as invalid.</t>

<t>The client <bcp14>SHOULD</bcp14> de-provision the resource record(s) provisioned for this challenge once the challenge is complete, i.e., once the "status" field of the challenge has the value "valid" or "invalid".</t>

</section>
<section anchor="security-considerations"><name>Security Considerations</name>

<t>As this challenge that is introduced only differs in the left-most label of the domain name from the existing <spanx style="verb">dns-01</spanx> challenge, the same security considerations apply.</t>

<t>In terms of the construction of the label prepended to the domain name, there is no need for a cryptographic hash. The purpose of that is to create a long-lived and statistically distinctive record of minimal size.</t>

<t>SHA-256 was picked due to its broad adoption, hardware support, and existing need in implementations that would likely support <spanx style="verb">dns-account-01</spanx>.</t>

<t>The first 10 bytes were picked as a tradeoff: the value needs to be short enough to not significantly impact DNS record and response size, long enough to provide sufficient probability of collision avoidance across ACME accounts, and just the right size to have Base32 require no padding. As the algorithm is used for uniform distribution of inputs, and not for integrity, we do not consider the trimming a security issue.</t>

</section>
<section anchor="iana-considerations"><name>IANA Considerations</name>

<section anchor="dns-parameters"><name>DNS Parameters</name>

<t>The Underscored and Globally Scoped DNS Node Names is to be updated to include the following entry:</t>

<figure><artwork><![CDATA[
RR Type: TXT
_NODE NAME: _acme-challenge_*
Reference: This document
]]></artwork></figure>

<t>Where <spanx style="verb">_acme-challenge_*</spanx> denotes all node names beginning with the string <spanx style="verb">_acme-challenge_</spanx>. It does NOT refer to a DNS wildcard specification.</t>

</section>
<section anchor="acme-validation-method"><name>ACME Validation Method</name>

<t>The "ACME Validation Methods" registry is to be updated to include the following entry:</t>

<figure><artwork><![CDATA[
label: dns-account-01
identifier-type: dns
ACME: Y
Reference: This document
]]></artwork></figure>

</section>
</section>


  </middle>

  <back>


    <references title='Normative References'>

<reference anchor="FIPS180-4" target="https://csrc.nist.gov/publications/detail/fips/180/4/final">
  <front>
    <title>Secure Hash Standard (SHS)</title>
    <author >
      <organization>National Institute of Standards and Technology</organization>
    </author>
    <date year="2015" month="August"/>
  </front>
</reference>


<reference anchor="RFC8555">
  <front>
    <title>Automatic Certificate Management Environment (ACME)</title>
    <author fullname="R. Barnes" initials="R." surname="Barnes"/>
    <author fullname="J. Hoffman-Andrews" initials="J." surname="Hoffman-Andrews"/>
    <author fullname="D. McCarney" initials="D." surname="McCarney"/>
    <author fullname="J. Kasten" initials="J." surname="Kasten"/>
    <date month="March" year="2019"/>
    <abstract>
      <t>Public Key Infrastructure using X.509 (PKIX) certificates are used for a number of purposes, the most significant of which is the authentication of domain names. Thus, certification authorities (CAs) in the Web PKI are trusted to verify that an applicant for a certificate legitimately represents the domain name(s) in the certificate. As of this writing, this verification is done through a collection of ad hoc mechanisms. This document describes a protocol that a CA and an applicant can use to automate the process of verification and certificate issuance. The protocol also provides facilities for other certificate management functions, such as certificate revocation.</t>
    </abstract>
  </front>
  <seriesInfo name="RFC" value="8555"/>
  <seriesInfo name="DOI" value="10.17487/RFC8555"/>
</reference>

<reference anchor="RFC2119">
  <front>
    <title>Key words for use in RFCs to Indicate Requirement Levels</title>
    <author fullname="S. Bradner" initials="S." surname="Bradner"/>
    <date month="March" year="1997"/>
    <abstract>
      <t>In many standards track documents several words are used to signify the requirements in the specification. These words are often capitalized. This document defines these words as they should be interpreted in IETF documents. This document specifies an Internet Best Current Practices for the Internet Community, and requests discussion and suggestions for improvements.</t>
    </abstract>
  </front>
  <seriesInfo name="BCP" value="14"/>
  <seriesInfo name="RFC" value="2119"/>
  <seriesInfo name="DOI" value="10.17487/RFC2119"/>
</reference>

<reference anchor="RFC8174">
  <front>
    <title>Ambiguity of Uppercase vs Lowercase in RFC 2119 Key Words</title>
    <author fullname="B. Leiba" initials="B." surname="Leiba"/>
    <date month="May" year="2017"/>
    <abstract>
      <t>RFC 2119 specifies common key words that may be used in protocol specifications. This document aims to reduce the ambiguity by clarifying that only UPPERCASE usage of the key words have the defined special meanings.</t>
    </abstract>
  </front>
  <seriesInfo name="BCP" value="14"/>
  <seriesInfo name="RFC" value="8174"/>
  <seriesInfo name="DOI" value="10.17487/RFC8174"/>
</reference>

<reference anchor="RFC4086">
  <front>
    <title>Randomness Requirements for Security</title>
    <author fullname="D. Eastlake 3rd" initials="D." surname="Eastlake 3rd"/>
    <author fullname="J. Schiller" initials="J." surname="Schiller"/>
    <author fullname="S. Crocker" initials="S." surname="Crocker"/>
    <date month="June" year="2005"/>
    <abstract>
      <t>Security systems are built on strong cryptographic algorithms that foil pattern analysis attempts. However, the security of these systems is dependent on generating secret quantities for passwords, cryptographic keys, and similar quantities. The use of pseudo-random processes to generate secret quantities can result in pseudo-security. A sophisticated attacker may find it easier to reproduce the environment that produced the secret quantities and to search the resulting small set of possibilities than to locate the quantities in the whole of the potential number space.</t>
      <t>Choosing random quantities to foil a resourceful and motivated adversary is surprisingly difficult. This document points out many pitfalls in using poor entropy sources or traditional pseudo-random number generation techniques for generating such quantities. It recommends the use of truly random hardware techniques and shows that the existing hardware on many systems can be used for this purpose. It provides suggestions to ameliorate the problem when a hardware solution is not available, and it gives examples of how large such quantities need to be for some applications. This document specifies an Internet Best Current Practices for the Internet Community, and requests discussion and suggestions for improvements.</t>
    </abstract>
  </front>
  <seriesInfo name="BCP" value="106"/>
  <seriesInfo name="RFC" value="4086"/>
  <seriesInfo name="DOI" value="10.17487/RFC4086"/>
</reference>

<reference anchor="RFC6234">
  <front>
    <title>US Secure Hash Algorithms (SHA and SHA-based HMAC and HKDF)</title>
    <author fullname="D. Eastlake 3rd" initials="D." surname="Eastlake 3rd"/>
    <author fullname="T. Hansen" initials="T." surname="Hansen"/>
    <date month="May" year="2011"/>
    <abstract>
      <t>Federal Information Processing Standard, FIPS</t>
    </abstract>
  </front>
  <seriesInfo name="RFC" value="6234"/>
  <seriesInfo name="DOI" value="10.17487/RFC6234"/>
</reference>

<reference anchor="RFC4648">
  <front>
    <title>The Base16, Base32, and Base64 Data Encodings</title>
    <author fullname="S. Josefsson" initials="S." surname="Josefsson"/>
    <date month="October" year="2006"/>
    <abstract>
      <t>This document describes the commonly used base 64, base 32, and base 16 encoding schemes. It also discusses the use of line-feeds in encoded data, use of padding in encoded data, use of non-alphabet characters in encoded data, use of different encoding alphabets, and canonical encodings. [STANDARDS-TRACK]</t>
    </abstract>
  </front>
  <seriesInfo name="RFC" value="4648"/>
  <seriesInfo name="DOI" value="10.17487/RFC4648"/>
</reference>




    </references>



<?line 229?>

<section numbered="false" anchor="acknowledgments"><name>Acknowledgments</name>

</section>


  </back>

<!-- ##markdown-source:
H4sIAAAAAAAAA51a63rbNhL9z6fAan+s3ZVkybFTR99eqtpO4taWE1+auvvt
V1MkJMEiCZYArShp+iz7LPtke2YAUpTk9LJ/LIkkBoOZM2cudKfTCayyiRyI
1rC0Og2tjMWxLKyaqAg/xEWYhVOZysyK0+xRFTrj7zvD44vTXXEyuhbn4Vgm
WPVO2Zmgy2IYRbrEQ2cn4ngWJonMprIVhONxIR9pIzzTwcrO8evh+fnp6NVp
K6C9prpYDoSxcRDEOsrCFFrFRTixHSXtpBNGqezEmcEXFt+JKtmd3n4Awc+C
sJDhQFzLqCyUXQYLXcynhS7zgfgjhwvmcoml8UDQloHKi4GYlEny7MWXR7Yo
jd3v9V7QljIr5SAQwu/x7hW+22UOtd9hZ5VNxSu6g6tpqBIn7is6S1cXU1wN
i2g2EDNrczPY24tDG9oijOay6FYP7S2me7RqLxzr0u7RXrByOYasUKcqVnu/
y0BYl+C8xq528+u7Tl5X6d8pKQhLO9MFjt2BVMGGca4aZlZnShsx7JLb4QGd
8SM4R5ipD6FVOhuIsyyWucQfGP1YZ7ZQY/im4Cels1MczjM9/sp9dDNpn9gs
VQVtdEmHeGKXV1pPE9kU6g/81ZTvdCOdbkv9Bn+N+DY0Vj6l+rbQh3jOD/+q
1JfaKiPOdTnX5ndJndCC5FdlXltIMEm4ICN8g+9zvTDz32cJg7ULZWRzgyDT
BeJDPTKgX569ue4f9ToHA15XMQQHlhSvQzNjBeKwiMXO9evr3RY/BwTjsf1e
/7DTO3Irw2IqG6iLTBF1objtTvXjXl6OEwpE6Gn2Ymmh3d5E5WYPe+8d4GsW
Jiymxpzw5xuIES8LE+DJQL8S0awntVZG4FPcyGiW6URPl0GgssnqhEGn0xHh
2FC42SC4mcE/oJySmQCBlqgMOAhFJheihj7cUgg7k47j8kJbHemkLWQW4hgI
9jDjW0GUKJJjNa6YhSwgKAb5qExEhHediMcwUTEfoCm+0GklQxhZPMoiKA0L
Zp4tpNFlEUmBzeYgMsivtVkxblfwaSAUgBBpmViVw/1mCZimBraDvjXTGRIy
g6kSuVKkY3TySNvSeUNBGuC2O0HXmQ6BhCVB8GdYHweKy4jOQoaU4p54o9e/
b5zM5DIC5UJn2MBIflgcdQ/IYx8//unq5fHR4eHhp0844k+lwjlxsNAGfDJn
TFOZTPKZvTlLsIhzyf2PTFn1lvfgO2SlymXB/c33N/cQH4HWvYXKTP1USv9c
hMRhyeWZUGkuY8VISFSqLFmCtsjKdIzd9CTQ+ElmBOyUNJUyTZ9CzBhaIi1O
OedYDcOdZc4dnUJO6SnQYKKX7Ia2WEAkDCXzsKBDho+IhXCsEqQx8UETGhkR
rIkBAwQEJSxtM9ArRo1InzAqtCETSsCpIFlaxTJuC51LCNeFAa6hVCgW4RKq
BXps6QDhavuokSOxiDVo1/in/atTExt1xTUMlYRFsmzDw8jlBmrAtx9koTux
XsBSWJGqacH2aQu70CJWkwnODDMbacucF5B0BGoBTi2AKZBNkELHSMv34AwP
yETDI9BK6ZjXQLazwhiO8UeLImkY3OyVoHEeA0+cwO8+ehwKMnra7/8ZKDXN
Z3UMrWYh+UMHuYrmqzhxoF1BH7EEA3rTIWc17Oa0xmXYPobSwf3xaHhxWuHU
qQikrlukK4ZNIQw2nSVeHzhKeDGgPOKN7ia/VdG4TXBUu7RdAFeJH4Hs42VV
AiQSR0LdZLb556riqNurc9I/RzDTntCxkujjDkloDAppbK43yG9z34rTwmy5
ZgAsrCItUPapeMQTqS4oeNhWkjdQEV1AfTb1VeuGgjBd4BxBkBkiaPSi5lOH
CVNFemkcHyMpPMoNsq+9vPRhCg2C2nB+0zafqqYYF7xe+BTwLJhGKEjjxzCL
1qCTJIHnzVisI6jWz9FbTEa3iIIkWZJxoekSFlSRQNhbv23gCNGpiqDIxKau
vHWmLd+orqFkbrMLyUcE98DIME0orhqPCNgj0RQQC5SdSLQsw1MwnDNFDHm3
y8yUlAnw8DKgkO8kSN2xN3y7FkB2M77gJ5MbcJ2jGVMhH/kFPpGGlVZEm7ED
DdAZVSnlN9JW0MxTRHgZw0eZjRCq90k1CG5J+XZcqoScTqoG2LLDZEZppV6G
87AxPeFDOdRkgFlTt0ZENmKxzpiNwFljKp9mKjUzDlvtySjSsRyDrZ3NwbVz
YoVY59bVM7FwBYjdCEREUY5WISPAE9N2qRRAMf9ISRGW56UnEgWc4t+uMiAA
LBiWrYvb65tW232K0SV/vzp9e3t2dXpC36+pM6y/BP6J69eXt+cnq2+rlceX
FxenoxO3GFfF2qWgdTG8a7mYaV2+uTm7HA3PWxROdo0ZKVvCNmPJKCngKwqa
0ASxNBH6FBeCXx+/+e9/+ge+ctnv91+gcvHw6H95gB9I5pnbjYnZ/SQGCMI8
l2HBgZwA8mGubEhoDpHfZ0iUgsoAWPOLf5Fl/j0QfxtHef/gH/4CHXjtYmWz
tYtss+0rW4udEZ+49MQ2tTXXrm9Yel3f4d3a78rujYt/+ycV2qLTP/rnPwKC
EA0FhsfHl7ejG+B8NTwIgndEdVweUONIUYnAkoTNqjCEb8yq0nb5lRb4apyY
0NFzVYQz34W2WjFe8n1lAFhXdFdFo09pPivTcjzvHgEw1DTj3aFHKaua2TFH
1ExCzYIJDuZkK3Yq5m6DmwvI3B0wMbsforUe+K0urdNzmOKphUNRAHNoIpwq
fDiXzADC2m4ua9fB7OnWLWGMcR2BpYlE0SH6+0diTGkV5pJkuBy548yKCo6V
PZiIIZU6KgnmATcTFfNmRDHPD8oiAerzGQjcUp0YJWVMh8xR/Hg2rBbvtP7e
2gXLSukD66B39ByBxdbF0771q3s6nTG/ru5467geh1YZ17o6A2WOsn755Zfg
I/eULXJGa7Bl77a7C83pZtXEyvchkTP1zW44w8bcU73exau7xfm7s/fVQsq3
paG1lE1xyOoGO5GuX56cHly+uzsY3czt3cMsvbvu9e7Su/75zfzw4mRqf7h5
+XB380M6evghubu5fd8KPrHewbAJ7EmZTBQIZYOnCdKyIBtVTcyE8u+CfqEd
xGHQzhFvu+ISwCWKds22nx80+rM2DdZ869YnZ1C/yumJT3PvMcRBFDuqXENa
VbJ4xf+yVhmwHmle+owHwursHz5Hk4B8ZaFEPZHAxr5Q39J17Sz0xNPR5yJd
eo9smMXVIr45WFu0TjawnBtGtDbahR9b4uefGfHP9nf8MXaeKo93/9UbvPj3
Lsvp1AdWpjo/4tDMaE+XzV3HiIzqLOvc8nz/GQziJNyzvPtKwmoV84BBhRxZ
d2uiCtgUZRAsQU3vjvvo1eXwCxedBgXX7srNsNmj0qUh5UjVege3vzvy9vZb
Sh88PziqlH6yb6CUvLloHYBfdp8BB6GpvFzKCm3n2s2TkEhDGg6A8JLY7cXD
idbPP7fu6wIJq2LXFRKN0ZfMs8nE06qhCHlT5QU/iWlOE7gQ3WA5j1qn2GpI
EVXgxMG2mxRCWRC8pAGN4xdw5OS3YEi2ai0Wi27FSbqYturmoA4wsiqO9HkG
w4N279Rd9T5pufaikUIXukQhWyfJjchxIyoyycBR62ZglA9pqh8n+4/Z4aGd
LmV3Q2/xrNcTZyMB44rWuf7p++juu6Nut/vwfvhwWn7f6754mB48f/f1M1yb
pPv99Kebs5Yjw52zzBfQSPCoAPFEq+FbjgC673JnZZ1v3n2LT/RcOTxtKwRt
UyAnxLEkYxQlo4T7h4myVXuUoxvuIpQB41xn66M5X5MzTEDVMs1R4evxA6As
dj5+2uWuKZqju0xkPJUrZVfE6bu4ldfBYDyIcUNCtsGbS+TjZjq6mh7G3/UP
Xs36b4PXmkb/Da8Hx2581Lnh1xUoS6tB7N6DNvKvD4bGeZQcWzTolIRZpKsa
4js+b4bJlLLY6TUIocptcxX/arZkrMnHy8m3s9Ht896iTooZQpCz8PX1vrlO
+m+syR9f/tA7mo/sh2/jP5aNG8en4fSn3TYfJlwmOtw4ir/nKjlUCST9bX98
ezX9Rp+aZHzSjw6BqGf5XXx9ca704Zfp29HooE7FlxkBX6pHVxMWDALjy0/v
/jr2XW9kQD6+EtvGW824KwSsp9g6kZYFD9B8fDbSKbW+en1m+vkmck1RXzCY
XykX/lia5qPGn8nWK1GfydU1u25Q2dZQgio+6drqlSjs8baUxZJLwCZrm3qY
+fS+WPidLKiBX4WjixguhGmG5JUgtqpkohSNnLbNDBAEZxNu92qGoqGGG0dy
s2zKKJJUydeE21BK+fvGoMhD5T0RmW5wLd2fwAA03i2a1wkjFRKFhz1OyLOJ
PHTzYUMQk9HcNLb2MODyfhKqZFMfkpuGxXyztqMxJT/Wdc2+x6RvKGPZWc8b
G13VjtldJRagxXlnrZjVbuLS3JTu+zkJkmVXdturp6ra21UAlbdWa2dr1UOL
VW+RDVv+HC0ealTvkrmyXI2WeCC4oSAjhce17pWI9O2/G3SbKr8kcmI7KQjZ
15p6O8nXBFBPiranU+3VKP4z4y9m9aV78YCuKq0n3DUX+UpnNYPzZfHq5dJm
N12w0YFAHrO7ZjcqlrnV0yLMZ+h4qWp1w8W8LHLkkrrPVjx4cqNIP8b3Mz3H
iNDa+OkkbEbnjuhtXQVoiEEbo1J0d0Z9oB66Yp8FXElDeCqr3GSf+tVxQYh3
wyx654DuMl7QhMeUea4L/+aktjAfSPHrn4T7Rm9EVt1VPomaUyft12/PyR3w
XXXd7/niekE289qFNKCwBQpTPZkMGvCjzY0fPZkZCZcZV+LWBSylJiaMzFIr
n+bokz8b7GSdtntLspLiuzIoP4EcDk1cGlcTRxg3Atf7IpdeGNGUuXqV1CRa
4+z2UBpHi4Wazizv6d4lwmFfu07A9+CEFt/id8XQBR3KBuQBO0sJFDw8JyiV
OCNSDzuf/yvA41NlyBJ+X7LGhAt3K6cE+jYsXPFahX9X6xUqTV1GrgNEGVNK
juuz4Wi4FdN/5gmUeBMWwDsNIpxHb6mCNxGnMdLhVQLDEUqvIzQSMa8ZaRh3
xP8+oCpPlnlc1Ypu2iE3kirNU5a+Wr66Eq4WQ0IJfhxdnpwKGuUPxGYZ/QWq
TH5xFtHDzfmlq0becZRuvsX68Yt7kDCMJPndMMwFbTLWdyynKuN5Vp1s/fhp
S8g9j354xk2jn4IU4fqVbbBQSRzRvwRU4y+2a5ftyhD6bpVGLiRKgdjZt/X0
TXA3vSmFLsv/06ZMagOxHqfBaoLYcf+sg/v8rnkg7n7Dtvzye4xqnSA0rIt2
HjMFHwfu/Y2M/96ahImRrU/B/wBG8o7GYCUAAA==

-->

</rfc>

